[{"confidence": "0.8781", "file_id": "41", "bbox": "95 416 140 462"}, {"confidence": "0.8723", "file_id": "41", "bbox": "1226 364 1272 409"}, {"confidence": "0.8603", "file_id": "13", "bbox": "785 393 824 436"}, {"confidence": "0.8583", "file_id": "49", "bbox": "1124 337 1167 376"}, {"confidence": "0.8554", "file_id": "9", "bbox": "1265 373 1307 420"}, {"confidence": "0.8458", "file_id": "26", "bbox": "835 363 893 423"}, {"confidence": "0.8397", "file_id": "9", "bbox": "169 413 212 462"}, {"confidence": "0.8330", "file_id": "21", "bbox": "761 351 810 397"}, {"confidence": "0.8196", "file_id": "67", "bbox": "1092 498 1131 537"}, {"confidence": "0.7971", "file_id": "5", "bbox": "1248 396 1315 468"}, {"confidence": "0.7917", "file_id": "68", "bbox": "1189 357 1269 436"}, {"confidence": "0.7760", "file_id": "49", "bbox": "287 328 333 368"}, {"confidence": "0.7504", "file_id": "60", "bbox": "1028 37 1143 137"}, {"confidence": "0.7199", "file_id": "43", "bbox": "1285 360 1307 383"}, {"confidence": "0.7124", "file_id": "39", "bbox": "677 439 713 472"}, {"confidence": "0.7040", "file_id": "11", "bbox": "794 452 823 484"}, {"confidence": "0.7036", "file_id": "11", "bbox": "455 471 487 504"}, {"confidence": "0.7002", "file_id": "0", "bbox": "716 439 738 461"}, {"confidence": "0.6988", "file_id": "0", "bbox": "418 419 444 445"}, {"confidence": "0.6611", "file_id": "70", "bbox": "824 543 850 566"}, {"confidence": "0.3797", "file_id": "60", "bbox": "1053 50 1108 128"}]